[
    {
        "icon": "bx bx-error",
        "content": "Curabitur id eros quis nunc suscipit blandit",
        "index":1
    },
    {
        "icon": "bx bx-package",
        "content": "Duis malesuada justo eu sapien elementum, in semper diam posuere",
        "index":2
    },
    {
        "icon": "bx bx-cart",
        "content": "Donec at nisi sit amet tortor commodo porttitor pretium a erat",
        "index":3
    },
    {
        "icon": "bx bx-error",
        "content": "In gravida mauris et nisi",
        "index":4
    },
    {
        "icon": "bx bx-cart",
        "content": "Curabitur id eros quis nunc suscipit blandit",
        "index":5
    }
]